Workbook

Sheet Untitled
A1: ID_Transaccion | B1: Region | C1: Cod_Verificado | D1: Fecha | E1: Sucursal | F1: Vendedor | G1: Categoria | H1: Producto | I1: Cantidad | J1: Precio_Unitario | K1: Costo_Unitario | L1: mes | M1: dia | N1: numero dia | O1: nombre del dia | P1: dia y mes | Q1: Proveedores | R1: Margen | S1: Proveedor_Oficial | T1: Comision_Estado
A2: TRX-1001 | B2: =LEFT(A2,2) -> TR | C2: =LEN(A2) -> 8 | D2: 46027 | E2: Corrientes | F2: Juan Perez | G2: Alimentos | H2: Yerba Mate 1kg | I2: 15 | J2: 3500 | K2: 2400 | L2: =MONTH(D2) -> 1 | M2: =DAY(D2) -> 5 | N2: =WEEKDAY(M2) -> 5 | O2: =TEXT(N2,"dddd") -> jueves | P2: =RIGHT(D2,5) -> 01-05 | Q2: {=IFERROR(_xlfn.XLOOKUP(H2, Maestro_Productos_Precios!$B:$B, Maestro_Productos_Precios!$D:$D),"Producto no encontrado")} -> Cooperativa Neike | R2: {=_xlfn.XLOOKUP(H2, Maestro_Productos_Precios!$B:$B, Maestro_Productos_Precios!$G:$G, "No Encontrado")} -> 0.31 | S2: {=IFERROR(INDEX(Maestro_Productos_Precios!$D:$D, MATCH(H2, Maestro_Productos_Precios!$B:$B, 0)),"Producto no encontrado")} -> Cooperativa Neike | T2: =IFERROR(IF(VLOOKUP(E2, Reporte_Consolidado_M1!$A$2:$B$4, 2, FALSE) > 50000, J2 * 0.05, J2 * 0.02),0) -> 175
A3: TRX-1002 | B3: =LEFT(A3,2) -> TR | C3: =LEN(A3) -> 8 | D3: 46028 | E3: Resistencia | F3: Maria Gomez | G3: Tecnologia | H3: Auriculares Bluetooth | I3: 4 | J3: 25000 | K3: 16000 | L3: =MONTH(D3) -> 1 | M3: =DAY(D3) -> 6 | N3: =WEEKDAY(M3) -> 6 | O3: =TEXT(N3,"dddd") -> viernes | P3: =RIGHT(D3,5) -> 01-06 | Q3: {=IFERROR(_xlfn.XLOOKUP(H3, Maestro_Productos_Precios!$B:$B, Maestro_Productos_Precios!$D:$D),"Producto no encontrado")} -> TechImport S.R.L. | R3: {=_xlfn.XLOOKUP(H3, Maestro_Productos_Precios!$B:$B, Maestro_Productos_Precios!$G:$G, "No Encontrado")} -> 0.36 | S3: {=IFERROR(INDEX(Maestro_Productos_Precios!$D:$D, MATCH(H3, Maestro_Productos_Precios!$B:$B, 0)),"Producto no encontrado")} -> TechImport S.R.L. | T3: =IFERROR(IF(VLOOKUP(E3, Reporte_Consolidado_M1!$A$2:$B$4, 2, FALSE) > 50000, J3 * 0.05, J3 * 0.02),0) -> 1250
A4: TRX-1003 | B4: =LEFT(A4,2) -> TR | C4: =LEN(A4) -> 8 | D4: 46028 | E4: Corrientes | F4: juan perez | G4: Alimentos | H4: Yerba Mate 1kg | I4: 8 | J4: 3500 | K4: 2400 | L4: =MONTH(D4) -> 1 | M4: =DAY(D4) -> 6 | N4: =WEEKDAY(M4) -> 6 | O4: =TEXT(N4,"dddd") -> viernes | P4: =RIGHT(D4,5) -> 01-06 | Q4: {=IFERROR(_xlfn.XLOOKUP(H4, Maestro_Productos_Precios!$B:$B, Maestro_Productos_Precios!$D:$D),"Producto no encontrado")} -> Cooperativa Neike | R4: {=_xlfn.XLOOKUP(H4, Maestro_Productos_Precios!$B:$B, Maestro_Productos_Precios!$G:$G, "No Encontrado")} -> 0.31 | S4: {=IFERROR(INDEX(Maestro_Productos_Precios!$D:$D, MATCH(H4, Maestro_Productos_Precios!$B:$B, 0)),"Producto no encontrado")} -> Cooperativa Neike | T4: =IFERROR(IF(VLOOKUP(E4, Reporte_Consolidado_M1!$A$2:$B$4, 2, FALSE) > 50000, J4 * 0.05, J4 * 0.02),0) -> 175
A5: TRX-1004 | B5: =LEFT(A5,2) -> TR | C5: =LEN(A5) -> 8 | D5: 46030 | E5: Posadas | F5: Carlos Ruiz | G5: Accesorios | H5: Correa Canina 3m | I5: 12 | J5: 8500 | K5: 5000 | L5: =MONTH(D5) -> 1 | M5: =DAY(D5) -> 8 | N5: =WEEKDAY(M5) -> 1 | O5: =TEXT(N5,"dddd") -> domingo | P5: =RIGHT(D5,5) -> 01-08 | Q5: {=IFERROR(_xlfn.XLOOKUP(H5, Maestro_Productos_Precios!$B:$B, Maestro_Productos_Precios!$D:$D),"Producto no encontrado")} -> PetStyle Litoral | R5: {=_xlfn.XLOOKUP(H5, Maestro_Productos_Precios!$B:$B, Maestro_Productos_Precios!$G:$G, "No Encontrado")} -> 0.41 | S5: {=IFERROR(INDEX(Maestro_Productos_Precios!$D:$D, MATCH(H5, Maestro_Productos_Precios!$B:$B, 0)),"Producto no encontrado")} -> PetStyle Litoral | T5: =IFERROR(IF(VLOOKUP(E5, Reporte_Consolidado_M1!$A$2:$B$4, 2, FALSE) > 50000, J5 * 0.05, J5 * 0.02),0) -> 425
A6: TRX-1005 | B6: =LEFT(A6,2) -> TR | C6: =LEN(A6) -> 8 | D6: 46032 | E6: Corrientes | F6: Maria Gomez | G6: Tecnologia | H6: Soporte Notebook | I6: 3 | J6: 18000 | K6: 11000 | L6: =MONTH(D6) -> 1 | M6: =DAY(D6) -> 10 | N6: =WEEKDAY(M6) -> 3 | O6: =TEXT(N6,"dddd") -> martes | P6: =RIGHT(D6,5) -> 01-10 | Q6: {=IFERROR(_xlfn.XLOOKUP(H6, Maestro_Productos_Precios!$B:$B, Maestro_Productos_Precios!$D:$D),"Producto no encontrado")} -> TechImport S.R.L. | R6: {=_xlfn.XLOOKUP(H6, Maestro_Productos_Precios!$B:$B, Maestro_Productos_Precios!$G:$G, "No Encontrado")} -> 0.38 | S6: {=IFERROR(INDEX(Maestro_Productos_Precios!$D:$D, MATCH(H6, Maestro_Productos_Precios!$B:$B, 0)),"Producto no encontrado")} -> TechImport S.R.L. | T6: =IFERROR(IF(VLOOKUP(E6, Reporte_Consolidado_M1!$A$2:$B$4, 2, FALSE) > 50000, J6 * 0.05, J6 * 0.02),0) -> 900
A7: TRX-1006 | B7: =LEFT(A7,2) -> TR | C7: =LEN(A7) -> 8 | D7: 46033 | E7: Resistencia | F7: Juan Perez | G7: Alimentos | H7: Alimento Perro 20kg | I7: 5 | J7: 42000 | K7: 30000 | L7: =MONTH(D7) -> 1 | M7: =DAY(D7) -> 11 | N7: =WEEKDAY(M7) -> 4 | O7: =TEXT(N7,"dddd") -> miércoles | P7: =RIGHT(D7,5) -> 01-11 | Q7: {=IFERROR(_xlfn.XLOOKUP(H7, Maestro_Productos_Precios!$B:$B, Maestro_Productos_Precios!$D:$D),"Producto no encontrado")} -> NutriDog Arg | R7: {=_xlfn.XLOOKUP(H7, Maestro_Productos_Precios!$B:$B, Maestro_Productos_Precios!$G:$G, "No Encontrado")} -> 0.28 | S7: {=IFERROR(INDEX(Maestro_Productos_Precios!$D:$D, MATCH(H7, Maestro_Productos_Precios!$B:$B, 0)),"Producto no encontrado")} -> NutriDog Arg | T7: =IFERROR(IF(VLOOKUP(E7, Reporte_Consolidado_M1!$A$2:$B$4, 2, FALSE) > 50000, J7 * 0.05, J7 * 0.02),0) -> 2100
A8: TRX-1007 | B8: =LEFT(A8,2) -> TR | C8: =LEN(A8) -> 8 | D8: 46034 | E8: Posadas | F8: Carlos Ruiz | G8: Alimentos | H8: Yerba Mate 1kg | I8: 20 | J8: 3500 | K8: 2400 | L8: =MONTH(D8) -> 1 | M8: =DAY(D8) -> 12 | N8: =WEEKDAY(M8) -> 5 | O8: =TEXT(N8,"dddd") -> jueves | P8: =RIGHT(D8,5) -> 01-12 | Q8: {=IFERROR(_xlfn.XLOOKUP(H8, Maestro_Productos_Precios!$B:$B, Maestro_Productos_Precios!$D:$D),"Producto no encontrado")} -> Cooperativa Neike | R8: {=_xlfn.XLOOKUP(H8, Maestro_Productos_Precios!$B:$B, Maestro_Productos_Precios!$G:$G, "No Encontrado")} -> 0.31 | S8: {=IFERROR(INDEX(Maestro_Productos_Precios!$D:$D, MATCH(H8, Maestro_Productos_Precios!$B:$B, 0)),"Producto no encontrado")} -> Cooperativa Neike | T8: =IFERROR(IF(VLOOKUP(E8, Reporte_Consolidado_M1!$A$2:$B$4, 2, FALSE) > 50000, J8 * 0.05, J8 * 0.02),0) -> 175
A9: TRX-1008 | B9: =LEFT(A9,2) -> TR | C9: =LEN(A9) -> 8 | D9: 46037 | E9: Corrientes | F9: Maria Gomez | G9: Accesorios | H9: Juguete Mordillo | I9: 15 | J9: 4500 | K9: 2500 | L9: =MONTH(D9) -> 1 | M9: =DAY(D9) -> 15 | N9: =WEEKDAY(M9) -> 1 | O9: =TEXT(N9,"dddd") -> domingo | P9: =RIGHT(D9,5) -> 01-15 | Q9: {=IFERROR(_xlfn.XLOOKUP(H9, Maestro_Productos_Precios!$B:$B, Maestro_Productos_Precios!$D:$D),"Producto no encontrado")} -> PetStyle Litoral | R9: {=_xlfn.XLOOKUP(H9, Maestro_Productos_Precios!$B:$B, Maestro_Productos_Precios!$G:$G, "No Encontrado")} -> 0.44 | S9: {=IFERROR(INDEX(Maestro_Productos_Precios!$D:$D, MATCH(H9, Maestro_Productos_Precios!$B:$B, 0)),"Producto no encontrado")} -> PetStyle Litoral | T9: =IFERROR(IF(VLOOKUP(E9, Reporte_Consolidado_M1!$A$2:$B$4, 2, FALSE) > 50000, J9 * 0.05, J9 * 0.02),0) -> 225
A10: TRX-1009 | B10: =LEFT(A10,2) -> TR | C10: =LEN(A10) -> 8 | D10: 46038 | E10: Resistencia | F10: Juan Perez | G10: Tecnologia | H10: Auriculares Bluetooth | I10: 6 | J10: 25000 | K10: 16000 | L10: =MONTH(D10) -> 1 | M10: =DAY(D10) -> 16 | N10: =WEEKDAY(M10) -> 2 | O10: =TEXT(N10,"dddd") -> lunes | P10: =RIGHT(D10,5) -> 01-16 | Q10: {=IFERROR(_xlfn.XLOOKUP(H10, Maestro_Productos_Precios!$B:$B, Maestro_Productos_Precios!$D:$D),"Producto no encontrado")} -> TechImport S.R.L. | R10: {=_xlfn.XLOOKUP(H10, Maestro_Productos_Precios!$B:$B, Maestro_Productos_Precios!$G:$G, "No Encontrado")} -> 0.36 | S10: {=IFERROR(INDEX(Maestro_Productos_Precios!$D:$D, MATCH(H10, Maestro_Productos_Precios!$B:$B, 0)),"Producto no encontrado")} -> TechImport S.R.L. | T10: =IFERROR(IF(VLOOKUP(E10, Reporte_Consolidado_M1!$A$2:$B$4, 2, FALSE) > 50000, J10 * 0.05, J10 * 0.02),0) -> 1250
A11: TRX-1010 | B11: =LEFT(A11,2) -> TR | C11: =LEN(A11) -> 8 | D11: 46040 | E11: Corrientes | F11: Carlos Ruiz | G11: Alimentos | H11: Alimento Gato 10kg | I11: 10 | J11: 28000 | K11: 19000 | L11: =MONTH(D11) -> 1 | M11: =DAY(D11) -> 18 | N11: =WEEKDAY(M11) -> 4 | O11: =TEXT(N11,"dddd") -> miércoles | P11: =RIGHT(D11,5) -> 01-18 | Q11: {=IFERROR(_xlfn.XLOOKUP(H11, Maestro_Productos_Precios!$B:$B, Maestro_Productos_Precios!$D:$D),"Producto no encontrado")} -> NutriDog Arg | R11: {=_xlfn.XLOOKUP(H11, Maestro_Productos_Precios!$B:$B, Maestro_Productos_Precios!$G:$G, "No Encontrado")} -> 0.32 | S11: {=IFERROR(INDEX(Maestro_Productos_Precios!$D:$D, MATCH(H11, Maestro_Productos_Precios!$B:$B, 0)),"Producto no encontrado")} -> NutriDog Arg | T11: =IFERROR(IF(VLOOKUP(E11, Reporte_Consolidado_M1!$A$2:$B$4, 2, FALSE) > 50000, J11 * 0.05, J11 * 0.02),0) -> 1400
A12: TRX-1011 | B12: =LEFT(A12,2) -> TR | C12: =LEN(A12) -> 8 | D12: 46042 | E12: Posadas | F12: Maria Gomez | G12: Alimentos | H12: Yerba Mate 1kg | I12: 14 | J12: 3500 | K12: 2400 | L12: =MONTH(D12) -> 1 | M12: =DAY(D12) -> 20 | N12: =WEEKDAY(M12) -> 6 | O12: =TEXT(N12,"dddd") -> viernes | P12: =RIGHT(D12,5) -> 01-20 | Q12: {=IFERROR(_xlfn.XLOOKUP(H12, Maestro_Productos_Precios!$B:$B, Maestro_Productos_Precios!$D:$D),"Producto no encontrado")} -> Cooperativa Neike | R12: {=_xlfn.XLOOKUP(H12, Maestro_Productos_Precios!$B:$B, Maestro_Productos_Precios!$G:$G, "No Encontrado")} -> 0.31 | S12: {=IFERROR(INDEX(Maestro_Productos_Precios!$D:$D, MATCH(H12, Maestro_Productos_Precios!$B:$B, 0)),"Producto no encontrado")} -> Cooperativa Neike | T12: =IFERROR(IF(VLOOKUP(E12, Reporte_Consolidado_M1!$A$2:$B$4, 2, FALSE) > 50000, J12 * 0.05, J12 * 0.02),0) -> 175
A13: TRX-1012 | B13: =LEFT(A13,2) -> TR | C13: =LEN(A13) -> 8 | D13: 46044 | E13: Resistencia | F13: Carlos Ruiz | G13: Accesorios | H13: Correa Canina 3m | I13: 9 | J13: 8500 | K13: 5000 | L13: =MONTH(D13) -> 1 | M13: =DAY(D13) -> 22 | N13: =WEEKDAY(M13) -> 1 | O13: =TEXT(N13,"dddd") -> domingo | P13: =RIGHT(D13,5) -> 01-22 | Q13: {=IFERROR(_xlfn.XLOOKUP(H13, Maestro_Productos_Precios!$B:$B, Maestro_Productos_Precios!$D:$D),"Producto no encontrado")} -> PetStyle Litoral | R13: {=_xlfn.XLOOKUP(H13, Maestro_Productos_Precios!$B:$B, Maestro_Productos_Precios!$G:$G, "No Encontrado")} -> 0.41 | S13: {=IFERROR(INDEX(Maestro_Productos_Precios!$D:$D, MATCH(H13, Maestro_Productos_Precios!$B:$B, 0)),"Producto no encontrado")} -> PetStyle Litoral | T13: =IFERROR(IF(VLOOKUP(E13, Reporte_Consolidado_M1!$A$2:$B$4, 2, FALSE) > 50000, J13 * 0.05, J13 * 0.02),0) -> 425
... A21: TRX-1020 | B21: =LEFT(A21,2) -> TR | C21: =LEN(A21) -> 8 | D21: 46065 | E21: Corrientes | F21: Carlos Ruiz | G21: Tecnologia | H21: Soporte Notebook | I21: 5 | J21: 18000 | K21: 11000 | L21: =MONTH(D21) -> 2 | M21: =DAY(D21) -> 12 | N21: =WEEKDAY(M21) -> 5 | O21: =TEXT(N21,"dddd") -> jueves | P21: =RIGHT(D21,5) -> 02-12 | Q21: {=IFERROR(_xlfn.XLOOKUP(H21, Maestro_Productos_Precios!$B:$B, Maestro_Productos_Precios!$D:$D),"Producto no encontrado")} -> TechImport S.R.L. | R21: {=_xlfn.XLOOKUP(H21, Maestro_Productos_Precios!$B:$B, Maestro_Productos_Precios!$G:$G, "No Encontrado")} -> 0.38 | S21: {=IFERROR(INDEX(Maestro_Productos_Precios!$D:$D, MATCH(H21, Maestro_Productos_Precios!$B:$B, 0)),"Producto no encontrado")} -> TechImport S.R.L. | T21: =IFERROR(IF(VLOOKUP(E21, Reporte_Consolidado_M1!$A$2:$B$4, 2, FALSE) > 50000, J21 * 0.05, J21 * 0.02),0) -> 900
B22: =LEFT(A22,2) | C22: =LEN(A22) -> 0 | H22: Agua Saborizada Guille | L22: =MONTH(D22) -> 12 | M22: =DAY(D22) -> 30 | N22: =WEEKDAY(M22) -> 2 | O22: =TEXT(N22,"dddd") -> lunes | P22: =RIGHT(D22,5) | Q22: {=IFERROR(_xlfn.XLOOKUP(H22, Maestro_Productos_Precios!$B:$B, Maestro_Productos_Precios!$D:$D),"Producto no encontrado")} -> Producto no encontrado | R22: {=_xlfn.XLOOKUP(H22, Maestro_Productos_Precios!$B:$B, Maestro_Productos_Precios!$G:$G, "No Encontrado")} -> No Encontrado | S22: {=IFERROR(INDEX(Maestro_Productos_Precios!$D:$D, MATCH(H22, Maestro_Productos_Precios!$B:$B, 0)),"Producto no encontrado")} -> Producto no encontrado | T22: =IFERROR(IF(VLOOKUP(E22, Reporte_Consolidado_M1!$A$2:$B$4, 2, FALSE) > 50000, J22 * 0.05, J22 * 0.02),0) -> 0

Sheet Reporte_Consolidado_M1
A1: Ciudad | B1: Total de Ventas
A2: =Untitled!E2 -> Corrientes | B2: =SUMIFS(Untitled!$J:$J, Untitled!$E:$E, "Corrientes") -> 101500
A3: =Untitled!E3 -> Resistencia | B3: =SUMIFS(Untitled!$J:$J, Untitled!$E:$E, "Resistencia") -> 129000
A4: Posadas | B4: =SUMIFS(Untitled!$J:$J, Untitled!$E:$E, "Posadas") -> 85500

Sheet Maestro_Productos_Precios
A1: SKU | B1: Producto | C1: Categoria | D1: Proveedor | E1: Precio_Lista | F1: Costo_Base | G1: Margen_Esperado
A2: SKU-501 | B2: Yerba Mate 1kg | C2: Alimentos | D2: Cooperativa Neike | E2: 3500 | F2: 2400 | G2: 0.31
A3: SKU-502 | B3: Auriculares Bluetooth | C3: Tecnologia | D3: TechImport S.R.L. | E3: 25000 | F3: 16000 | G3: 0.36
A4: SKU-503 | B4: Correa Canina 3m | C4: Accesorios | D4: PetStyle Litoral | E4: 8500 | F4: 5000 | G4: 0.41
A5: SKU-504 | B5: Soporte Notebook | C5: Tecnologia | D5: TechImport S.R.L. | E5: 18000 | F5: 11000 | G5: 0.38
A6: SKU-505 | B6: Alimento Perro 20kg | C6: Alimentos | D6: NutriDog Arg | E6: 42000 | F6: 30000 | G6: 0.28
A7: SKU-506 | B7: Juguete Mordillo | C7: Accesorios | D7: PetStyle Litoral | E7: 4500 | F7: 2500 | G7: 0.44
A8: SKU-507 | B8: Alimento Gato 10kg | C8: Alimentos | D8: NutriDog Arg | E8: 28000 | F8: 19000 | G8: 0.32

Sheet TD_Resumen_Ejecutivo.

Sheet Datos limpios
